{
	"dohel" :
	{
		"class" : "fouMarshal",
		"female" : true,
		"texts" :
		{
			"name" : "Dohel",
			"biography" : "Chociaz posiada niezwykle jak na zombie umiejetnosci (a przede wszystkim potrafi myslec i planowac!). W Dejii uchodzil tylko za jednego z zolnierzy. Don dohel przylaczyl sie do Kastore'a tak szybko jak tylko zdolal",
			"specialty" :
			{
				"description" : "{Guardsman and Veteran Guardsman}\r\n\r\nIncreases Speed of any Guardsman or Veteran Guardsman by 1 and their Attack and Defense skills by 5% for every 2 levels (rounded up)",
				"tooltip" : "Creature Bonus: Guardsman",
				"name" : "Guardsman"
			}
		},
		"images" :
		{
			"specialtySmall" : "celestial/heroes/dohel/spec-small.png",
			"specialtyLarge" : "celestial/heroes/dohel/spec-large.png",
			"large" : "celestial/heroes/dohel/portrait-large.png",
			"small" : "celestial/heroes/dohel/portrait-small.png"
		},

		"spellbook" :
		[
			"haste"
		],
		"army" :
		[
			{ "creature" : "ftGuardsman", "min" :  10, "max" : 15 },
			{ "creature" : "ftGuardsman", "min" :  8, "max" :  10 },
			{ "creature" : "ftGuardsman", "min" :  5, "max" :  8 }
		],
		"skills" :
		[
			{
				"level" : "basic",
				"skill" : "wisdom"
			},
			{
				"level" : "basic",
				"skill" : "airMagic"
			}
		],
		"specialty" : {
			"creature" : "ftGuardsman"
		}
	}
}
